pyEMA/__init__.py
pyEMA/normal_modes.py
pyEMA/pole_picking.py
pyEMA/pyEMA.py
pyEMA/stabilization.py
pyEMA/tools.py
pyEMA-0.26.dist-info/LICENSE
pyEMA-0.26.dist-info/METADATA
pyEMA-0.26.dist-info/WHEEL
pyEMA-0.26.dist-info/top_level.txt
pyEMA-0.26.dist-info/RECORD
