Metadata-Version: 2.1
Name: pyEMA
Version: 0.26
Summary: Experimental and operational modal analysis.
Home-page: https://github.com/ladisk/pyEMA
Author: Klemen Zaletelj, Domen Gorjup, Janko Slavič, Tomaž Bregar, Miha Pogačar, et al.
Maintainer: Janko Slavič
Maintainer-email: janko.slavic@fs.uni-lj.si
License: UNKNOWN
Platform: UNKNOWN
License-File: LICENSE
Requires-Dist: tqdm (>=4.23.4)
Requires-Dist: numpy (>=1.14.3)
Requires-Dist: matplotlib (>=3.3.1)
Requires-Dist: scipy (>=1.1.0)
Requires-Dist: pytest (>=3.0.5)
